Workbook
Name Costos_Fijos: '06_COSTOS'!$B$8
Name Costo_Var_Unitario: '06_COSTOS'!$B$15
Name Precio_Venta_Unitario: '06_COSTOS'!$B$17
Name Unidades_Vendidas: '06_COSTOS'!$B$18
Name Ingresos_Totales: ='09_ESTADO_RESULTADOS'!$B$3
Name Utilidad_Bruta: ='09_ESTADO_RESULTADOS'!$B$5
Name Utilidad_Operativa: ='09_ESTADO_RESULTADOS'!$B$7
Name Utilidad_Neta: ='09_ESTADO_RESULTADOS'!$B$11
Name Gastos_Financieros: ='09_ESTADO_RESULTADOS'!$B$8
Name Egresos_Totales: ='05_EGRESOS'!$F$20
Name Costo_Total_Tonelada: ='19_COSTO_POR_TONELADA'!B8
Name Tasa_BCV: '02_CONFIGURACION'!$B$7

Sheet 01_PORTADA
B2: SISTEMA INTEGRAL DE GESTION FINANCIERA
B7: [NOMBRE DE LA EMPRESA]
B9: RIF: | D9: J-00000000-0
B10: Direccion: | D10: [Direccion fiscal]
B11: Ano fiscal: | D11: 2026
B12: Moneda principal: | D12: Bs / USD
B13: Fecha de actualizacion: | D13: 46184
B15: MENU DE NAVEGACION
B16: 00_MANUAL
B17: 02_CONFIGURACION
B18: 03_DASHBOARD_EJECUTIVO
B19: 04_INGRESOS
B20: 05_EGRESOS
B21: 06_COSTOS
B22: 07_PUNTO_EQUILIBRIO
B23: 08_FLUJO_CAJA
B24: 09_ESTADO_RESULTADOS
B25: 10_BALANCE_GENERAL
B26: 11_CUENTAS_POR_COBRAR
... B36: 21_INDICADORES_MINEROS

Sheet 00_MANUAL
A1: MANUAL DE USO Y MANUAL TECNICO
A3: MANUAL DE USUARIO
A4: 1. Navegacion
A5: Use los enlaces de la hoja 01_PORTADA o las pestanas inferiores para moverse entre modulos.
A6: 2. Configuracion inicial
A7: Antes de usar el archivo, complete 02_CONFIGURACION: datos de la empresa, RIF, tasa BCV,
A8: alicuotas de IVA/IGTF, centros de costos, lineas de negocio y categorias.
A9: 3. Registro de operaciones
A10: Ingrese cada transaccion en 04_INGRESOS y 05_EGRESOS dentro de las tablas (tbl_Ingresos /
A11: tbl_Egresos). Al escribir una nueva fila debajo de la tabla, esta se expande automaticamente
A12: y todas las formulas, dashboards y reportes se recalculan solos.
A13: 4. Categorias
... A61: frontend (Power Apps o aplicacion web a medida).

Sheet 02_CONFIGURACION
A1: PARAMETROS GENERALES DE LA EMPRESA
A3: Nombre de la empresa | B3: [NOMBRE DE LA EMPRESA]
A4: RIF | B4: J-00000000-0
A5: Direccion | B5: [Direccion fiscal]
A6: Moneda principal | B6: Bs
A7: Tasa BCV (Bs/USD) | B7: 36.5
A8: Alicuota IVA general | B8: 0.16
A9: Alicuota IGTF | B9: 0.03
A10: Ano fiscal | B10: 2026
A12: CENTROS DE COSTOS
A13: Administracion
A14: Ventas
A15: Produccion
A16: Logistica
A17: Mina
A19: LINEAS DE NEGOCIO / PROYECTOS
A20: Linea A
A21: Linea B
A22: Proyecto Minero 1
A24: CATEGORIAS DE INGRESOS
A25: Ventas
... A39: Otros gastos

Sheet 03_DASHBOARD_EJECUTIVO
A1: DASHBOARD EJECUTIVO
A3: Ingresos del Mes (Bs.) | D3: Ingresos del Ano (Bs.) | G3: Egresos del Mes (Bs.) | J3: Egresos del Ano (Bs.)
A4: =SUMPRODUCT((MONTH(tbl_Ingresos[Fecha])=MONTH(TODAY()))*(YEAR(tbl_Ingresos[Fecha])=YEAR(TODAY()))*tbl_Ingresos[Bs.]) | D4: =SUMPRODUCT((YEAR(tbl_Ingresos[Fecha])=YEAR(TODAY()))*tbl_Ingresos[Bs.]) | G4: =SUMPRODUCT((MONTH(tbl_Egresos[Fecha])=MONTH(TODAY()))*(YEAR(tbl_Egresos[Fecha])=YEAR(TODAY()))*tbl_Egresos[Bs.]) | J4: =SUMPRODUCT((YEAR(tbl_Egresos[Fecha])=YEAR(TODAY()))*tbl_Egresos[Bs.])
A7: Utilidad Bruta (Bs.) | D7: Utilidad Operativa (Bs.) | G7: Utilidad Neta (Bs.) | J7: EBITDA (Bs.)
A8: =Utilidad_Bruta | D8: =Utilidad_Operativa | G8: =Utilidad_Neta | J8: =Utilidad_Operativa
A11: Liquidez (veces) | D11: Capital de Trabajo (Bs.) | G11: Endeudamiento (%) | J11: Margen Neto (%)
A12: 1.5 | D12: 250000 | G12: 0.45 | J12: =Utilidad_Neta/Ingresos_Totales
A16: VENTAS / INGRESOS POR CATEGORIA | I16: EGRESOS POR CATEGORIA
A17: Ventas | B17: =SUMIFS(tbl_Ingresos[Bs.],tbl_Ingresos[Categoria],A17) | I17: Nomina | J17: =SUMIFS(tbl_Egresos[Bs.],tbl_Egresos[Categoria],I17)
A18: Servicios | B18: =SUMIFS(tbl_Ingresos[Bs.],tbl_Ingresos[Categoria],A18) | I18: Combustible | J18: =SUMIFS(tbl_Egresos[Bs.],tbl_Egresos[Categoria],I18)
A19: Exportaciones | B19: =SUMIFS(tbl_Ingresos[Bs.],tbl_Ingresos[Categoria],A19) | I19: Transporte | J19: =SUMIFS(tbl_Egresos[Bs.],tbl_Egresos[Categoria],I19)
A20: Otros ingresos | B20: =SUMIFS(tbl_Ingresos[Bs.],tbl_Ingresos[Categoria],A20) | I20: Mantenimiento | J20: =SUMIFS(tbl_Egresos[Bs.],tbl_Egresos[Categoria],I20)
I21: Servicios | J21: =SUMIFS(tbl_Egresos[Bs.],tbl_Egresos[Categoria],I21)
I22: Impuestos | J22: =SUMIFS(tbl_Egresos[Bs.],tbl_Egresos[Categoria],I22)
I23: Compras | J23: =SUMIFS(tbl_Egresos[Bs.],tbl_Egresos[Categoria],I23)
I24: Gastos Financieros | J24: =SUMIFS(tbl_Egresos[Bs.],tbl_Egresos[Categoria],I24)
I25: Otros gastos | J25: =SUMIFS(tbl_Egresos[Bs.],tbl_Egresos[Categoria],I25)
A28: SEMAFORO DE LIQUIDEZ
A29: Liquidez actual | B29: =B12 | C29: =IF(B29>=1.5,"VERDE",IF(B29>=1,"AMARILLO","ROJO"))

Sheet 04_INGRESOS
A1: 04 INGRESOS
A3: Fecha | B3: Cliente | C3: Concepto | D3: Categoria | E3: Centro de Costos | F3: Bs. | G3: USD
A4: 46027 | B4: Cliente A | C4: Venta de producto X | D4: Ventas | E4: Ventas | F4: 45000 | G4: =F4/Tasa_BCV
A5: 46034 | B5: Cliente B | C5: Servicio de mantenimiento | D5: Servicios | E5: Produccion | F5: 18000 | G5: =F5/Tasa_BCV
A6: 46056 | B6: Cliente C | C6: Exportacion lote 1 | D6: Exportaciones | E6: Logistica | F6: 120000 | G6: =F6/Tasa_BCV
A7: 46073 | B7: Cliente A | C7: Venta de producto Y | D7: Ventas | E7: Ventas | F7: 60000 | G7: =F7/Tasa_BCV
A8: 46089 | B8: Cliente D | C8: Otros ingresos varios | D8: Otros ingresos | E8: Administracion | F8: 5000 | G8: =F8/Tasa_BCV
A9: 46096 | B9: Cliente B | C9: Venta de producto X | D9: Ventas | E9: Ventas | F9: 75000 | G9: =F9/Tasa_BCV
A10: 46114 | B10: Cliente E | C10: Servicio tecnico | D10: Servicios | E10: Produccion | F10: 22000 | G10: =F10/Tasa_BCV
A11: 46130 | B11: Cliente C | C11: Exportacion lote 2 | D11: Exportaciones | E11: Logistica | F11: 135000 | G11: =F11/Tasa_BCV
A12: 46152 | B12: Cliente A | C12: Venta de producto Z | D12: Ventas | E12: Ventas | F12: 80000 | G12: =F12/Tasa_BCV
A13: 46167 | B13: Cliente F | C13: Servicio de consultoria | D13: Servicios | E13: Administracion | F13: 30000 | G13: =F13/Tasa_BCV
A14: 46174 | B14: Cliente B | C14: Venta mensual | D14: Ventas | E14: Ventas | F14: 90000 | G14: =F14/Tasa_BCV
A15: 46182 | B15: Cliente C | C15: Exportacion lote 3 | D15: Exportaciones | E15: Logistica | F15: 150000 | G15: =F15/Tasa_BCV
E17: TOTAL | F17: =SUBTOTAL(109,tbl_Ingresos[Bs.]) | G17: =SUBTOTAL(109,tbl_Ingresos[USD])

Sheet 05_EGRESOS
A1: 05 EGRESOS
A3: Fecha | B3: Proveedor | C3: Concepto | D3: Categoria | E3: Centro de Costos | F3: Bs. | G3: USD
A4: 46027 | B4: Nomina | C4: Pago quincenal nomina | D4: Nomina | E4: Administracion | F4: 30000 | G4: =F4/Tasa_BCV
A5: 46032 | B5: PDVSA | C5: Combustible flota | D5: Combustible | E5: Logistica | F5: 8000 | G5: =F5/Tasa_BCV
A6: 46042 | B6: Transportes XYZ | C6: Flete materiales | D6: Transporte | E6: Logistica | F6: 6000 | G6: =F6/Tasa_BCV
A7: 46058 | B7: Nomina | C7: Pago quincenal nomina | D7: Nomina | E7: Administracion | F7: 30000 | G7: =F7/Tasa_BCV
A8: 46061 | B8: Taller Mecanico | C8: Mantenimiento equipos | D8: Mantenimiento | E8: Produccion | F8: 9000 | G8: =F8/Tasa_BCV
A9: 46081 | B9: SENIAT | C9: IVA del periodo | D9: Impuestos | E9: Administracion | F9: 12000 | G9: =F9/Tasa_BCV
A10: 46086 | B10: Nomina | C10: Pago quincenal nomina | D10: Nomina | E10: Administracion | F10: 31000 | G10: =F10/Tasa_BCV
A11: 46096 | B11: Proveedor Insumos | C11: Compra materia prima | D11: Compras | E11: Produccion | F11: 40000 | G11: =F11/Tasa_BCV
A12: 46111 | B12: Banco | C12: Intereses prestamo | D12: Gastos Financieros | E12: Administracion | F12: 4000 | G12: =F12/Tasa_BCV
A13: 46117 | B13: Nomina | C13: Pago quincenal nomina | D13: Nomina | E13: Administracion | F13: 31000 | G13: =F13/Tasa_BCV
A14: 46124 | B14: Electricidad CORPOELEC | C14: Servicio electrico | D14: Servicios | E14: Produccion | F14: 7000 | G14: =F14/Tasa_BCV
A15: 46147 | B15: Nomina | C15: Pago quincenal nomina | D15: Nomina | E15: Administracion | F15: 32000 | G15: =F15/Tasa_BCV
... A18: 46181 | B18: PDVSA | C18: Combustible flota | D18: Combustible | E18: Logistica | F18: 9000 | G18: =F18/Tasa_BCV
E20: TOTAL | F20: =SUBTOTAL(109,tbl_Egresos[Bs.]) | G20: =SUBTOTAL(109,tbl_Egresos[USD])

Sheet 06_COSTOS
A1: ESTRUCTURA DE COSTOS
A3: COSTOS FIJOS MENSUALES
A4: Nomina administrativa | B4: 32000
A5: Seguros | B5: 3000
A6: Arrendamientos | B6: 8000
A7: Servicios (luz, agua, internet) | B7: 4000
A8: TOTAL COSTOS FIJOS | B8: =SUM(B4:B7)
A10: COSTOS VARIABLES (por unidad)
A11: Materia prima | B11: 80
A12: Transporte | B12: 15
A13: Combustible | B13: 10
A14: Comercializacion | B14: 5
A15: COSTO VARIABLE UNITARIO TOTAL | B15: =SUM(B11:B14)
A17: PRECIO DE VENTA UNITARIO | B17: 180
A18: UNIDADES VENDIDAS (mes) | B18: 1200

Sheet 07_PUNTO_EQUILIBRIO
A1: PUNTO DE EQUILIBRIO
A4: Costos Fijos (Bs.) | B4: =Costos_Fijos
A5: Precio de Venta Unitario (Bs.) | B5: =Precio_Venta_Unitario
A6: Costo Variable Unitario (Bs.) | B6: =Costo_Var_Unitario
A7: Margen de Contribucion Unitario (Bs.) | B7: =B5-B6
A8: Punto de Equilibrio (unidades) | B8: =B4/B7
A9: Punto de Equilibrio (Bs.) | B9: =B8*B5
A10: Punto de Equilibrio (USD) | B10: =B9/Tasa_BCV
A11: Unidades Vendidas Actuales | B11: =Unidades_Vendidas
A12: Margen de Seguridad (unidades) | B12: =B11-B8
A13: Margen de Seguridad (%) | B13: =B12/B11
A15: SIMULACION DE ESCENARIOS
A16: Escenario | B16: Var. Precio (%) | C16: Var. Costo Var. (%) | D16: Nuevo PE (unid.)
A17: Optimista | B17: 0.1 | C17: -0.05 | D17: =$B$4/(($B$5*(1+B17))-($B$6*(1+C17)))
A18: Base | B18: 0 | C18: 0 | D18: =$B$4/(($B$5*(1+B18))-($B$6*(1+C18)))
A19: Pesimista | B19: -0.1 | C19: 0.1 | D19: =$B$4/(($B$5*(1+B19))-($B$6*(1+C19)))

Sheet 08_FLUJO_CAJA
A1: FLUJO DE CAJA MENSUAL
A3: Mes | B3: Entradas (Bs.) | C3: Salidas (Bs.) | D3: Flujo Neto (Bs.) | E3: Saldo Acumulado (Bs.)
A4: Enero | B4: =SUMPRODUCT((MONTH(tbl_Ingresos[Fecha])=1)*(YEAR(tbl_Ingresos[Fecha])='02_CONFIGURACION'!$B$8)*tbl_Ingresos[Bs.]) | C4: =SUMPRODUCT((MONTH(tbl_Egresos[Fecha])=1)*(YEAR(tbl_Egresos[Fecha])='02_CONFIGURACION'!$B$8)*tbl_Egresos[Bs.]) | D4: =B4-C4 | E4: =D4
A5: Febrero | B5: =SUMPRODUCT((MONTH(tbl_Ingresos[Fecha])=2)*(YEAR(tbl_Ingresos[Fecha])='02_CONFIGURACION'!$B$8)*tbl_Ingresos[Bs.]) | C5: =SUMPRODUCT((MONTH(tbl_Egresos[Fecha])=2)*(YEAR(tbl_Egresos[Fecha])='02_CONFIGURACION'!$B$8)*tbl_Egresos[Bs.]) | D5: =B5-C5 | E5: =E4+D5
A6: Marzo | B6: =SUMPRODUCT((MONTH(tbl_Ingresos[Fecha])=3)*(YEAR(tbl_Ingresos[Fecha])='02_CONFIGURACION'!$B$8)*tbl_Ingresos[Bs.]) | C6: =SUMPRODUCT((MONTH(tbl_Egresos[Fecha])=3)*(YEAR(tbl_Egresos[Fecha])='02_CONFIGURACION'!$B$8)*tbl_Egresos[Bs.]) | D6: =B6-C6 | E6: =E5+D6
A7: Abril | B7: =SUMPRODUCT((MONTH(tbl_Ingresos[Fecha])=4)*(YEAR(tbl_Ingresos[Fecha])='02_CONFIGURACION'!$B$8)*tbl_Ingresos[Bs.]) | C7: =SUMPRODUCT((MONTH(tbl_Egresos[Fecha])=4)*(YEAR(tbl_Egresos[Fecha])='02_CONFIGURACION'!$B$8)*tbl_Egresos[Bs.]) | D7: =B7-C7 | E7: =E6+D7
A8: Mayo | B8: =SUMPRODUCT((MONTH(tbl_Ingresos[Fecha])=5)*(YEAR(tbl_Ingresos[Fecha])='02_CONFIGURACION'!$B$8)*tbl_Ingresos[Bs.]) | C8: =SUMPRODUCT((MONTH(tbl_Egresos[Fecha])=5)*(YEAR(tbl_Egresos[Fecha])='02_CONFIGURACION'!$B$8)*tbl_Egresos[Bs.]) | D8: =B8-C8 | E8: =E7+D8
A9: Junio | B9: =SUMPRODUCT((MONTH(tbl_Ingresos[Fecha])=6)*(YEAR(tbl_Ingresos[Fecha])='02_CONFIGURACION'!$B$8)*tbl_Ingresos[Bs.]) | C9: =SUMPRODUCT((MONTH(tbl_Egresos[Fecha])=6)*(YEAR(tbl_Egresos[Fecha])='02_CONFIGURACION'!$B$8)*tbl_Egresos[Bs.]) | D9: =B9-C9 | E9: =E8+D9
A10: Julio | B10: =SUMPRODUCT((MONTH(tbl_Ingresos[Fecha])=7)*(YEAR(tbl_Ingresos[Fecha])='02_CONFIGURACION'!$B$8)*tbl_Ingresos[Bs.]) | C10: =SUMPRODUCT((MONTH(tbl_Egresos[Fecha])=7)*(YEAR(tbl_Egresos[Fecha])='02_CONFIGURACION'!$B$8)*tbl_Egresos[Bs.]) | D10: =B10-C10 | E10: =E9+D10
A11: Agosto | B11: =SUMPRODUCT((MONTH(tbl_Ingresos[Fecha])=8)*(YEAR(tbl_Ingresos[Fecha])='02_CONFIGURACION'!$B$8)*tbl_Ingresos[Bs.]) | C11: =SUMPRODUCT((MONTH(tbl_Egresos[Fecha])=8)*(YEAR(tbl_Egresos[Fecha])='02_CONFIGURACION'!$B$8)*tbl_Egresos[Bs.]) | D11: =B11-C11 | E11: =E10+D11
A12: Septiembre | B12: =SUMPRODUCT((MONTH(tbl_Ingresos[Fecha])=9)*(YEAR(tbl_Ingresos[Fecha])='02_CONFIGURACION'!$B$8)*tbl_Ingresos[Bs.]) | C12: =SUMPRODUCT((MONTH(tbl_Egresos[Fecha])=9)*(YEAR(tbl_Egresos[Fecha])='02_CONFIGURACION'!$B$8)*tbl_Egresos[Bs.]) | D12: =B12-C12 | E12: =E11+D12
A13: Octubre | B13: =SUMPRODUCT((MONTH(tbl_Ingresos[Fecha])=10)*(YEAR(tbl_Ingresos[Fecha])='02_CONFIGURACION'!$B$8)*tbl_Ingresos[Bs.]) | C13: =SUMPRODUCT((MONTH(tbl_Egresos[Fecha])=10)*(YEAR(tbl_Egresos[Fecha])='02_CONFIGURACION'!$B$8)*tbl_Egresos[Bs.]) | D13: =B13-C13 | E13: =E12+D13
A14: Noviembre | B14: =SUMPRODUCT((MONTH(tbl_Ingresos[Fecha])=11)*(YEAR(tbl_Ingresos[Fecha])='02_CONFIGURACION'!$B$8)*tbl_Ingresos[Bs.]) | C14: =SUMPRODUCT((MONTH(tbl_Egresos[Fecha])=11)*(YEAR(tbl_Egresos[Fecha])='02_CONFIGURACION'!$B$8)*tbl_Egresos[Bs.]) | D14: =B14-C14 | E14: =E13+D14
A15: Diciembre | B15: =SUMPRODUCT((MONTH(tbl_Ingresos[Fecha])=12)*(YEAR(tbl_Ingresos[Fecha])='02_CONFIGURACION'!$B$8)*tbl_Ingresos[Bs.]) | C15: =SUMPRODUCT((MONTH(tbl_Egresos[Fecha])=12)*(YEAR(tbl_Egresos[Fecha])='02_CONFIGURACION'!$B$8)*tbl_Egresos[Bs.]) | D15: =B15-C15 | E15: =E14+D15
A17: PROYECCIONES (a partir del flujo neto promedio mensual)
A18: Horizonte | B18: Dias | C18: Flujo Proyectado (Bs.)
A19: 30 dias | B19: 30 | C19: =(AVERAGE(D4:D15)/30)*B19
A20: 90 dias | B20: 90 | C20: =(AVERAGE(D4:D15)/30)*B20
A21: 180 dias | B21: 180 | C21: =(AVERAGE(D4:D15)/30)*B21
A22: 365 dias | B22: 365 | C22: =(AVERAGE(D4:D15)/30)*B22

Sheet 09_ESTADO_RESULTADOS
A1: ESTADO DE RESULTADOS
A3: Ingresos | B3: =SUMIFS(tbl_Ingresos[Bs.],tbl_Ingresos[Categoria],"Ventas")+SUMIFS(tbl_Ingresos[Bs.],tbl_Ingresos[Categoria],"Servicios")+SUMIFS(tbl_Ingresos[Bs.],tbl_Ingresos[Categoria],"Exportaciones")+SUMIFS(tbl_Ingresos[Bs.],tbl_Ingresos[Categoria],"Otros ingresos")
A4: (-) Costo de Ventas (Compras) | B4: =SUMIFS(tbl_Egresos[Bs.],tbl_Egresos[Categoria],"Compras")
A5: =UTILIDAD BRUTA | B5: =B4-B5
A6: (-) Gastos Operativos | B6: =SUMIFS(tbl_Egresos[Bs.],tbl_Egresos[Categoria],"Nomina")+SUMIFS(tbl_Egresos[Bs.],tbl_Egresos[Categoria],"Combustible")+SUMIFS(tbl_Egresos[Bs.],tbl_Egresos[Categoria],"Transporte")+SUMIFS(tbl_Egresos[Bs.],tbl_Egresos[Categoria],"Mantenimiento")+SUMIFS(tbl_Egresos[Bs.],tbl_Egresos[Categoria],"Servicios")+SUMIFS(tbl_Egresos[Bs.],tbl_Egresos[Categoria],"Otros gastos")
A7: =UTILIDAD OPERATIVA (EBIT) | B7: =B6-B7
A8: (-) Gastos Financieros | B8: =SUMIFS(tbl_Egresos[Bs.],tbl_Egresos[Categoria],"Gastos Financieros")
A9: =UTILIDAD ANTES DE IMPUESTOS | B9: =B8-B9
A10: (-) Impuestos | B10: =SUMIFS(tbl_Egresos[Bs.],tbl_Egresos[Categoria],"Impuestos")
A11: =UTILIDAD NETA | B11: =B10-B11

Sheet 10_BALANCE_GENERAL
A1: BALANCE GENERAL
A3: ACTIVOS
A4: Activos Corrientes
A5: Caja y Bancos | B5: ='08_FLUJO_CAJA'!E15
A6: Cuentas por Cobrar | B6: =SUMIFS('11_CUENTAS_POR_COBRAR'!E:E,'11_CUENTAS_POR_COBRAR'!F:F,"Pendiente")
A7: Inventario | B7: ='13_INVENTARIO'!F100
A8: Total Activos Corrientes | B8: =SUM(B5:B7)
A10: Activos No Corrientes
A11: Propiedad, Planta y Equipo | B11: 800000
A12: Depreciacion Acumulada | B12: -120000
A13: Total Activos No Corrientes | B13: =SUM(B11:B12)
A14: TOTAL ACTIVOS | B14: =B8+B13
A16: PASIVOS
A17: Pasivos Corrientes
A18: Cuentas por Pagar | B18: =SUMIFS('12_CUENTAS_POR_PAGAR'!D:D,'12_CUENTAS_POR_PAGAR'!E:E,"Pendiente")
A19: Impuestos por Pagar | B19: 25000
A20: Prestamos a Corto Plazo | B20: 50000
A21: Total Pasivos Corrientes | B21: =SUM(B18:B20)
A23: Pasivos No Corrientes
A24: Prestamos a Largo Plazo | B24: 200000
A25: Total Pasivos No Corrientes | B25: =SUM(B24:B24)
A26: TOTAL PASIVOS | B26: =B21+B25
A28: PATRIMONIO
A29: Capital Social | B29: 300000
A30: Utilidades Retenidas | B30: 100000
A31: Utilidad del Ejercicio | B31: =Utilidad_Neta
A32: TOTAL PATRIMONIO | B32: =SUM(B29:B31)
A34: TOTAL PASIVO + PATRIMONIO | B34: =B26+B32
A36: INDICADORES FINANCIEROS
A37: Liquidez (Activo Cte. / Pasivo Cte.) | B37: =B8/B21
A38: Solvencia (Total Activos / Total Pasivos) | B38: =B14/B26
A39: Endeudamiento (Total Pasivos / Total Activos) | B39: =B26/B14

Sheet 11_CUENTAS_POR_COBRAR
A1: CUENTAS POR COBRAR
A3: Cliente | B3: Factura | C3: Fecha Emision | D3: Fecha Vencimiento | E3: Monto (Bs.) | F3: Estado | G3: Semaforo
A4: Cliente A | B4: FAC-001 | C4: 46143 | D4: 46174 | E4: 45000 | F4: Pendiente | G4: =IF(F4="Pagado","VERDE",IF(D4<TODAY(),"ROJO",IF(D4<=TODAY()+15,"AMARILLO","VERDE")))
A5: Cliente B | B5: FAC-002 | C5: 46152 | D5: 46183 | E5: 18000 | F5: Pendiente | G5: =IF(F5="Pagado","VERDE",IF(D5<TODAY(),"ROJO",IF(D5<=TODAY()+15,"AMARILLO","VERDE")))
A6: Cliente C | B6: FAC-003 | C6: 46127 | D6: 46157 | E6: 120000 | F6: Pendiente | G6: =IF(F6="Pagado","VERDE",IF(D6<TODAY(),"ROJO",IF(D6<=TODAY()+15,"AMARILLO","VERDE")))
A7: Cliente D | B7: FAC-004 | C7: 46162 | D7: 46193 | E7: 5000 | F7: Pagado | G7: =IF(F7="Pagado","VERDE",IF(D7<TODAY(),"ROJO",IF(D7<=TODAY()+15,"AMARILLO","VERDE")))

Sheet 12_CUENTAS_POR_PAGAR
A1: CUENTAS POR PAGAR
A3: Proveedor / Obligacion | B3: Tipo | C3: Fecha Vencimiento | D3: Monto (Bs.) | E3: Estado | F3: Alerta
A4: Proveedor Insumos | B4: Compras | C4: 46193 | D4: 45000 | E4: Pendiente | F4: =IF(E4="Pagado","Al dia",IF(C4<TODAY(),"VENCIDO",IF(C4<=TODAY()+7,"PROXIMO A VENCER","Al dia")))
A5: SENIAT - IVA | B5: Impuestos | C5: 46188 | D5: 12000 | E5: Pendiente | F5: =IF(E5="Pagado","Al dia",IF(C5<TODAY(),"VENCIDO",IF(C5<=TODAY()+7,"PROXIMO A VENCER","Al dia")))
A6: Banco - Cuota Prestamo | B6: Creditos | C6: 46203 | D6: 8000 | E6: Pendiente | F6: =IF(E6="Pagado","Al dia",IF(C6<TODAY(),"VENCIDO",IF(C6<=TODAY()+7,"PROXIMO A VENCER","Al dia")))
A7: Taller Mecanico | B7: Compras | C7: 46143 | D7: 9000 | E7: Pagado | F7: =IF(E7="Pagado","Al dia",IF(C7<TODAY(),"VENCIDO",IF(C7<=TODAY()+7,"PROXIMO A VENCER","Al dia")))

Sheet 13_INVENTARIO
A1: CONTROL DE INVENTARIO
A3: Producto | B3: Existencia | C3: Stock Minimo | D3: Stock Maximo | E3: Costo Unitario (Bs.) | F3: Valor Inventario (Bs.) | G3: Rotacion (veces/mes) | H3: Cobertura (dias)
A4: Producto X | B4: 500 | C4: 100 | D4: 1000 | E4: 80 | F4: =B4*E4 | G4: 6 | H4: 30
A5: Producto Y | B5: 200 | C5: 50 | D5: 500 | E5: 120 | F5: =B5*E5 | G5: 4 | H5: 22
A6: Producto Z | B6: 80 | C6: 100 | D6: 600 | E6: 150 | F6: =B6*E6 | G6: 2 | H6: 15
A7: Materia Prima A | B7: 1200 | C7: 300 | D7: 3000 | E7: 25 | F7: =B7*E7 | G7: 8 | H7: 28
E99: VALOR TOTAL INVENTARIO
F100: =SUM(F4:F7)

Sheet 14_NOMINA
A1: NOMINA - LEGISLACION LABORAL VENEZOLANA (LOTTT, IVSS, INCES, FAOV)
A3: Empleado | B3: Cargo | C3: Salario Mensual (Bs.) | D3: Dias Trabajados | E3: IVSS Trabajador (4%) | F3: FAOV Trabajador (1%) | G3: Aporte Trabajador | H3: IVSS Patrono (9%) | I3: FAOV Patrono (2%) | J3: INCES Patrono (2%) | K3: Salario Neto (Bs.)
A4: Empleado 1 | B4: Gerente Administrativo | C4: 15000 | D4: 30 | E4: =C4*0.04 | F4: =C4*0.01 | G4: =E4+F4 | H4: =C4*0.09 | I4: =C4*0.02 | J4: =C4*0.02 | K4: =C4-G4
A5: Empleado 2 | B5: Analista Financiero | C5: 9000 | D5: 30 | E5: =C5*0.04 | F5: =C5*0.01 | G5: =E5+F5 | H5: =C5*0.09 | I5: =C5*0.02 | J5: =C5*0.02 | K5: =C5-G5
A6: Empleado 3 | B6: Operador de Planta | C6: 6000 | D6: 30 | E6: =C6*0.04 | F6: =C6*0.01 | G6: =E6+F6 | H6: =C6*0.09 | I6: =C6*0.02 | J6: =C6*0.02 | K6: =C6-G6
A7: Empleado 4 | B7: Conductor | C7: 5500 | D7: 30 | E7: =C7*0.04 | F7: =C7*0.01 | G7: =E7+F7 | H7: =C7*0.09 | I7: =C7*0.02 | J7: =C7*0.02 | K7: =C7-G7
B8: TOTALES | C8: =SUM(C4:C7) | E8: =SUM(E4:E7) | F8: =SUM(F4:F7) | G8: =SUM(G4:G7) | H8: =SUM(H4:H7) | I8: =SUM(I4:I7) | J8: =SUM(J4:J7) | K8: =SUM(K4:K7)
A11: PRESTACIONES SOCIALES, VACACIONES Y UTILIDADES (Estimacion Anual)
A12: Empleado | B12: Salario Mensual (Bs.) | C12: Prestaciones (15 dias x 12 meses) | D12: Vacaciones (15 dias) | E12: Utilidades (30 dias min. LOTTT)
A13: Empleado 1 | B13: =C4 | C13: =(C4/30)*15*12 | D13: =(C4/30)*15 | E13: =(C4/30)*30
A14: Empleado 2 | B14: =C5 | C14: =(C5/30)*15*12 | D14: =(C5/30)*15 | E14: =(C5/30)*30
A15: Empleado 3 | B15: =C6 | C15: =(C6/30)*15*12 | D15: =(C6/30)*15 | E15: =(C6/30)*30
A16: Empleado 4 | B16: =C7 | C16: =(C7/30)*15*12 | D16: =(C7/30)*15 | E16: =(C7/30)*30

Sheet 15_IMPUESTOS
A1: CONTROL TRIBUTARIO - SENIAT Y MUNICIPAL
A3: SENIAT - IVA
A4: IVA Debito Fiscal (Ventas x Alicuota) | B4: =Ingresos_Totales*'02_CONFIGURACION'!$B$6
A5: IVA Credito Fiscal (Compras x Alicuota) | B5: =SUMIFS(tbl_Egresos[Bs.],tbl_Egresos[Categoria],"Compras")*'02_CONFIGURACION'!$B$6
A6: IVA a Pagar (Debito - Credito) | B6: =B4-B5
A8: RETENCIONES
A9: Retencion IVA (75% sobre IVA causado) | B9: =B5*0.75
A10: Retencion ISLR (estimado 2% sobre compras) | B10: =SUMIFS(tbl_Egresos[Bs.],tbl_Egresos[Categoria],"Compras")*0.02
A12: IGTF (Pagos en divisas)
A13: IGTF Estimado (Egresos USD x Alicuota) | B13: =Egresos_Totales/Tasa_BCV*'02_CONFIGURACION'!$B$7
A15: IMPUESTOS MUNICIPALES
A16: Impuesto Actividades Economicas (1% s/Ingresos) | B16: =Ingresos_Totales*0.01
A17: Impuesto Publicidad y Propaganda | B17: 1500
A18: Impuesto Inmuebles Urbanos | B18: 2500

Sheet 16_PRESUPUESTO
A1: PRESUPUESTO: PRESUPUESTADO VS EJECUTADO
A3: Concepto | B3: Presupuestado (Bs.) | C3: Ejecutado (Bs.) | D3: Variacion Absoluta (Bs.) | E3: Variacion (%)
A4: Ingresos | B4: 700000 | C4: =Ingresos_Totales | D4: =C4-B4 | E4: =D4/B4
A5: Costo de Ventas | B5: 180000 | C5: =SUMIFS(tbl_Egresos[Bs.],tbl_Egresos[Categoria],"Compras") | D5: =C5-B5 | E5: =D5/B5
A6: Gastos Operativos | B6: 250000 | C6: =SUMIFS(tbl_Egresos[Bs.],tbl_Egresos[Categoria],"Nomina")+SUMIFS(tbl_Egresos[Bs.],tbl_Egresos[Categoria],"Combustible")+SUMIFS(tbl_Egresos[Bs.],tbl_Egresos[Categoria],"Transporte")+SUMIFS(tbl_Egresos[Bs.],tbl_Egresos[Categoria],"Mantenimiento")+SUMIFS(tbl_Egresos[Bs.],tbl_Egresos[Categoria],"Servicios")+SUMIFS(tbl_Egresos[Bs.],tbl_Egresos[Categoria],"Otros gastos") | D6: =C6-B6 | E6: =D6/B6
A7: Gastos Financieros | B7: 15000 | C7: =Gastos_Financieros | D7: =C7-B7 | E7: =D7/B7

Sheet 17_KPI_GERENCIALES
A1: KPI GERENCIALES
A3: FINANCIEROS
A4: EBITDA (Bs.) | B4: =Utilidad_Operativa
A5: ROI (Utilidad Neta / Total Activos) | B5: =Utilidad_Neta/'10_BALANCE_GENERAL'!B14
A6: ROA (Utilidad Operativa / Total Activos) | B6: =Utilidad_Operativa/'10_BALANCE_GENERAL'!B14
A7: ROE (Utilidad Neta / Patrimonio) | B7: =Utilidad_Neta/'10_BALANCE_GENERAL'!B32
A8: Margen Neto | B8: =Utilidad_Neta/Ingresos_Totales
A9: Liquidez | B9: ='10_BALANCE_GENERAL'!B8/'10_BALANCE_GENERAL'!B21
A11: COMERCIALES
A12: Crecimiento de Ventas (vs presupuesto) | B12: ='16_PRESUPUESTO'!E4
A13: Clientes Activos (con CxC) | B13: =COUNTA(tbl_CxC[Cliente])
A15: OPERATIVOS
A16: Productividad (Ingresos / Nro. Empleados) | B16: =Ingresos_Totales/4
A17: Eficiencia (Utilidad Operativa / Ingresos) | B17: =Utilidad_Operativa/Ingresos_Totales

Sheet 18_PRODUCCION_MINERA
A1: PRODUCCION MINERA
A3: Fecha | B3: Mina | C3: Mineral | D3: Produccion (Tm) | E3: Ventas (Tm) | F3: Inventario (Tm)
A4: 46053 | B4: Mina 1 | C4: Oro | D4: 120 | E4: 110 | F4: =SUM(D$4:D4)-SUM(E$4:E4)
A5: 46081 | B5: Mina 1 | C5: Oro | D5: 135 | E5: 130 | F5: =SUM(D$4:D5)-SUM(E$4:E5)
A6: 46112 | B6: Mina 1 | C6: Oro | D6: 140 | E6: 138 | F6: =SUM(D$4:D6)-SUM(E$4:E6)
A7: 46142 | B7: Mina 2 | C7: Hierro | D7: 5000 | E7: 4800 | F7: =SUM(D$4:D7)-SUM(E$4:E7)
A8: 46173 | B8: Mina 2 | C8: Hierro | D8: 5200 | E8: 5100 | F8: =SUM(D$4:D8)-SUM(E$4:E8)

Sheet 19_COSTO_POR_TONELADA
A1: COSTO POR TONELADA
A3: Costo de Extraccion (Bs./Tm) | B3: 35
A4: Costo de Carga (Bs./Tm) | B4: 8
A5: Costo de Transporte (Bs./Tm) | B5: 12
A6: Costo de Beneficio (Bs./Tm) | B6: 20
A7: Costo de Comercializacion (Bs./Tm) | B7: 5
A8: COSTO TOTAL POR TONELADA | B8: =SUM(B3:B7)

Sheet 20_RESERVAS_MINERAS
A1: RESERVAS MINERAS
A3: Mina | B3: Reservas Medidas (Tm) | C3: Reservas Indicadas (Tm) | D3: Reservas Inferidas (Tm) | E3: Vida Util (anos)
A4: Mina 1 | B4: 50000 | C4: 30000 | D4: 20000 | E4: =B4/SUMPRODUCT((tbl_ProduccionMinera[Mina]=A4)*tbl_ProduccionMinera[Produccion (Tm)])*1
A5: Mina 2 | B5: 800000 | C5: 500000 | D5: 300000 | E5: =B5/SUMPRODUCT((tbl_ProduccionMinera[Mina]=A5)*tbl_ProduccionMinera[Produccion (Tm)])*1

Sheet 21_INDICADORES_MINEROS
A1: INDICADORES MINEROS
A4: Produccion Mensual (ultimo periodo, Tm) | B4: =INDEX(tbl_ProduccionMinera[Produccion (Tm)],COUNTA(tbl_ProduccionMinera[Mina]))
A5: Produccion Anual (Tm) | B5: =SUM(tbl_ProduccionMinera[Produccion (Tm)])
A6: Cumplimiento Plan de Explotacion (%) | B6: =B5/600000
A7: Productividad por Trabajador (Tm/trabajador) | B7: =B5/4
A8: Productividad por Equipo (Tm/equipo, 5 equipos) | B8: =B5/5
A9: Costo por Tonelada (Bs.) | B9: =Costo_Total_Tonelada
A10: Utilidad por Tonelada (Bs.) | B10: =Precio_Venta_Unitario-Costo_Total_Tonelada
A11: Indice de Accidentabilidad (accidentes/100 trab.) | B11: 0
A12: Cumplimiento Ambiental (%) | B12: 0.95
